fm_comfyui_bridge/__init__.py
fm_comfyui_bridge/bridge.py
fm_comfyui_bridge/comfy_api.py
fm_comfyui_bridge/config.py
fm_comfyui_bridge/lora_yaml.py
fm_comfyui_bridge/py.typed
fm_comfyui_bridge/Workflow/SDXL_Base.json
fm_comfyui_bridge/Workflow/SDXL_Base_API.json
fm_comfyui_bridge/Workflow/SDXL_HighReso.json
fm_comfyui_bridge/Workflow/SDXL_HighReso_API.json
fm_comfyui_bridge/Workflow/SDXL_HighReso_I2I.json
fm_comfyui_bridge/Workflow/SDXL_HighReso_I2I_API.json
fm_comfyui_bridge-0.9.1.dist-info/METADATA
fm_comfyui_bridge-0.9.1.dist-info/WHEEL
fm_comfyui_bridge-0.9.1.dist-info/licenses/LICENSE
fm_comfyui_bridge-0.9.1.dist-info/RECORD
