Metadata-Version: 2.4
Name: fm-comfyui-bridge
Version: 0.9.1
Summary: ComfyUI access bridge
Project-URL: Homepage, https://github.com/rerofumi/fm_comfyui_bridge
Author-email: rerofumi <rero2@yuumu.org>
License-File: LICENSE
Classifier: Development Status :: 3 - Alpha
Classifier: Intended Audience :: Developers
Classifier: License :: OSI Approved :: MIT License
Classifier: Operating System :: OS Independent
Classifier: Programming Language :: Python :: 3
Classifier: Topic :: Software Development :: Libraries :: Python Modules
Requires-Python: >=3.10
Requires-Dist: pillow>=11.0.0
Requires-Dist: pyyaml>=6.0.2
Requires-Dist: requests>=2.32.3
